{
  "timestamp": "2025-12-19T13:24:35.514676",
  "user_id": "c90b83da-7931-47d5-b0f5-1fdd427156f5",
  "query": "@AutoReleasedFx.cs list out all the methods",
  "cleaned_query": "list out all the methods",
  "rerank_enabled": false,
  "file_filters": [
    "C:\\Users\\CPU12391\\Desktop\\GDD_RAG_Gradio\\codebase_RAG\\tank_online_1-dev\\Assets\\_GameModules\\TankFusionModule\\Scripts\\Effects\\AutoReleasedFx.cs"
  ],
  "context_retrieval": {
    "query": "list out all the methods",
    "rerank_enabled": false,
    "hyde_v2_generation": {
      "total_time": 0.64,
      "ttft": 0.27,
      "token_count": 8,
      "token_rate": 21.4,
      "response_length": 127
    },
    "vector_search_time": 0.76,
    "total_time": 1.4,
    "context_length": 46,
    "results_count": {
      "methods": 0,
      "classes": 0
    }
  },
  "answer_generation": {
    "total_time": 0.49,
    "ttft": 0.29,
    "token_count": 6,
    "token_rate": 30.6,
    "response_length": 51
  },
  "total_time": 1.89
}